[
  {
    "movie_id": 1,
    "person_id": 137,
    "name": "Michael Mann"
  },
  {
    "movie_id": 2,
    "person_id": 160,
    "name": "Ilya Naishuller"
  },
  {
    "movie_id": 3,
    "person_id": 318,
    "name": "Jeff Fowler"
  },
  {
    "movie_id": 4,
    "person_id": 530,
    "name": "Mike Mitchell"
  },
  {
    "movie_id": 5,
    "person_id": 693,
    "name": "Jalmari Helander"
  },
  {
    "movie_id": 6,
    "person_id": 812,
    "name": "Robert D. Krzykowski"
  },
  {
    "movie_id": 7,
    "person_id": 890,
    "name": "Walter Hill"
  },
  {
    "movie_id": 8,
    "person_id": 931,
    "name": "Akira Kurosawa"
  },
  {
    "movie_id": 9,
    "person_id": 953,
    "name": "Carl Reiner"
  },
  {
    "movie_id": 10,
    "person_id": 1007,
    "name": "John Francis Daley"
  },
  {
    "movie_id": 10,
    "person_id": 1006,
    "name": "Jonathan Goldstein"
  },
  {
    "movie_id": 11,
    "person_id": 318,
    "name": "Jeff Fowler"
  },
  {
    "movie_id": 12,
    "person_id": 1375,
    "name": "Tony Cervone"
  },
  {
    "movie_id": 13,
    "person_id": 1431,
    "name": "Ralph Bakshi"
  },
  {
    "movie_id": 14,
    "person_id": 1865,
    "name": "Nikolaj Arcel"
  },
  {
    "movie_id": 15,
    "person_id": 1431,
    "name": "Ralph Bakshi"
  },
  {
    "movie_id": 16,
    "person_id": 2103,
    "name": "Eric Tsang Chi-Wai"
  },
  {
    "movie_id": 17,
    "person_id": 2164,
    "name": "Karyn Kusama"
  },
  {
    "movie_id": 18,
    "person_id": 2355,
    "name": "Alfred Hitchcock"
  },
  {
    "movie_id": 19,
    "person_id": 2402,
    "name": "Adam Wingard"
  },
  {
    "movie_id": 20,
    "person_id": 2604,
    "name": "J.C. Chandor"
  },
  {
    "movie_id": 21,
    "person_id": 2664,
    "name": "Eli Roth"
  },
  {
    "movie_id": 22,
    "person_id": 2723,
    "name": "Gene Wilder"
  },
  {
    "movie_id": 23,
    "person_id": 2756,
    "name": "Mel Brooks"
  },
  {
    "movie_id": 24,
    "person_id": 2856,
    "name": "Theodore Melfi"
  },
  {
    "movie_id": 25,
    "person_id": 2984,
    "name": "Stuart Rosenberg"
  },
  {
    "movie_id": 26,
    "person_id": 3009,
    "name": "John Krasinski"
  },
  {
    "movie_id": 27,
    "person_id": 210,
    "name": "David Leitch"
  },
  {
    "movie_id": 28,
    "person_id": 3248,
    "name": "Michael Davis"
  },
  {
    "movie_id": 29,
    "person_id": 3621,
    "name": "Scott Beck"
  },
  {
    "movie_id": 29,
    "person_id": 3622,
    "name": "Bryan Woods"
  },
  {
    "movie_id": 30,
    "person_id": 3650,
    "name": "Richard Rush"
  },
  {
    "movie_id": 31,
    "person_id": 3737,
    "name": "Martin Brest"
  },
  {
    "movie_id": 32,
    "person_id": 4074,
    "name": "Tanya Wexler"
  },
  {
    "movie_id": 33,
    "person_id": 4154,
    "name": "George P. Cosmatos"
  },
  {
    "movie_id": 34,
    "person_id": 4357,
    "name": "Denis Villeneuve"
  },
  {
    "movie_id": 35,
    "person_id": 4357,
    "name": "Denis Villeneuve"
  },
  {
    "movie_id": 36,
    "person_id": 4571,
    "name": "Luke Cormican"
  },
  {
    "movie_id": 37,
    "person_id": 4596,
    "name": "Newt Arnold"
  },
  {
    "movie_id": 38,
    "person_id": 4860,
    "name": "Simon McQuoid"
  },
  {
    "movie_id": 39,
    "person_id": 4922,
    "name": "Jay Roach"
  },
  {
    "movie_id": 40,
    "person_id": 5028,
    "name": "Brian De Palma"
  },
  {
    "movie_id": 41,
    "person_id": 5274,
    "name": "Roger Michell"
  },
  {
    "movie_id": 42,
    "person_id": 5323,
    "name": "Victor Cook"
  },
  {
    "movie_id": 43,
    "person_id": 5354,
    "name": "Joel Coen"
  },
  {
    "movie_id": 44,
    "person_id": 5419,
    "name": "Joe Johnston"
  },
  {
    "movie_id": 45,
    "person_id": 5993,
    "name": "Aki Kaurismki"
  },
  {
    "movie_id": 46,
    "person_id": 6029,
    "name": "Joe Sichta"
  },
  {
    "movie_id": 47,
    "person_id": 6052,
    "name": "Robert Moore"
  },
  {
    "movie_id": 48,
    "person_id": 6118,
    "name": "Michael Ritchie"
  },
  {
    "movie_id": 49,
    "person_id": 6196,
    "name": "Julius Onah"
  },
  {
    "movie_id": 50,
    "person_id": 210,
    "name": "David Leitch"
  },
  {
    "movie_id": 51,
    "person_id": 6927,
    "name": "W.S. Van Dyke"
  },
  {
    "movie_id": 52,
    "person_id": 6960,
    "name": "Pierre Morel"
  },
  {
    "movie_id": 53,
    "person_id": 7474,
    "name": "Ruben Fleischer"
  },
  {
    "movie_id": 54,
    "person_id": 7546,
    "name": "Bob Saget"
  },
  {
    "movie_id": 55,
    "person_id": 7679,
    "name": "Lana Wachowski"
  },
  {
    "movie_id": 55,
    "person_id": 7680,
    "name": "Lilly Wachowski"
  },
  {
    "movie_id": 56,
    "person_id": 7754,
    "name": "Grant Heslov"
  },
  {
    "movie_id": 57,
    "person_id": 7995,
    "name": "Ryan Coogler"
  },
  {
    "movie_id": 58,
    "person_id": 8110,
    "name": "Woody Allen"
  },
  {
    "movie_id": 59,
    "person_id": 8186,
    "name": "Robert Rodriguez"
  },
  {
    "movie_id": 60,
    "person_id": 8336,
    "name": "Cameron Cairnes"
  },
  {
    "movie_id": 60,
    "person_id": 8333,
    "name": "Colin Cairnes"
  },
  {
    "movie_id": 61,
    "person_id": 8398,
    "name": "Simon West"
  },
  {
    "movie_id": 62,
    "person_id": 4922,
    "name": "Jay Roach"
  },
  {
    "movie_id": 63,
    "person_id": 8635,
    "name": "Don Siegel"
  },
  {
    "movie_id": 64,
    "person_id": 8702,
    "name": "Lee Won-tae"
  },
  {
    "movie_id": 65,
    "person_id": 8730,
    "name": "Scott Jeralds"
  },
  {
    "movie_id": 66,
    "person_id": 8760,
    "name": "Prachya Pinkaew"
  },
  {
    "movie_id": 67,
    "person_id": 8826,
    "name": "Jeremiah S. Chechik"
  },
  {
    "movie_id": 68,
    "person_id": 8874,
    "name": "Wolfgang Petersen"
  },
  {
    "movie_id": 69,
    "person_id": 2355,
    "name": "Alfred Hitchcock"
  },
  {
    "movie_id": 70,
    "person_id": 9016,
    "name": "Martin Scorsese"
  },
  {
    "movie_id": 71,
    "person_id": 9257,
    "name": "David Lowery"
  },
  {
    "movie_id": 72,
    "person_id": 9373,
    "name": "Rick Friedberg"
  },
  {
    "movie_id": 73,
    "person_id": 9446,
    "name": "Tony Scott"
  },
  {
    "movie_id": 74,
    "person_id": 9580,
    "name": "Peter Howitt"
  },
  {
    "movie_id": 75,
    "person_id": 9632,
    "name": "Olatunde Osunsanmi"
  },
  {
    "movie_id": 76,
    "person_id": 9774,
    "name": "John Badham"
  },
  {
    "movie_id": 77,
    "person_id": 6927,
    "name": "W.S. Van Dyke"
  },
  {
    "movie_id": 78,
    "person_id": 2756,
    "name": "Mel Brooks"
  },
  {
    "movie_id": 79,
    "person_id": 9955,
    "name": "Andy Serkis"
  },
  {
    "movie_id": 80,
    "person_id": 10018,
    "name": "Edward Hall"
  },
  {
    "movie_id": 81,
    "person_id": 7733,
    "name": "George Clooney"
  },
  {
    "movie_id": 82,
    "person_id": 10124,
    "name": "Michael Bay"
  },
  {
    "movie_id": 83,
    "person_id": 10166,
    "name": "Gene Quintano"
  },
  {
    "movie_id": 84,
    "person_id": 10260,
    "name": "Aleksi Delikouras"
  },
  {
    "movie_id": 85,
    "person_id": 10289,
    "name": "Mike Judge"
  },
  {
    "movie_id": 86,
    "person_id": 10384,
    "name": "David Zucker"
  },
  {
    "movie_id": 87,
    "person_id": 10444,
    "name": "Christopher Guest"
  },
  {
    "movie_id": 88,
    "person_id": 10650,
    "name": "Greta Gerwig"
  },
  {
    "movie_id": 89,
    "person_id": 7476,
    "name": "Kelly Marcel"
  },
  {
    "movie_id": 90,
    "person_id": 8110,
    "name": "Woody Allen"
  },
  {
    "movie_id": 91,
    "person_id": 10854,
    "name": "Oliver Parker"
  },
  {
    "movie_id": 92,
    "person_id": 2355,
    "name": "Alfred Hitchcock"
  },
  {
    "movie_id": 93,
    "person_id": 10990,
    "name": "David Kerr"
  },
  {
    "movie_id": 94,
    "person_id": 11059,
    "name": "Corey Yuen Kwai"
  },
  {
    "movie_id": 95,
    "person_id": 11198,
    "name": "Fernando Meirelles"
  },
  {
    "movie_id": 96,
    "person_id": 11227,
    "name": "George Miller"
  },
  {
    "movie_id": 97,
    "person_id": 890,
    "name": "Walter Hill"
  },
  {
    "movie_id": 98,
    "person_id": 10384,
    "name": "David Zucker"
  },
  {
    "movie_id": 99,
    "person_id": 11447,
    "name": "Sebastin Cordero"
  },
  {
    "movie_id": 100,
    "person_id": 11534,
    "name": "Wes Anderson"
  },
  {
    "movie_id": 101,
    "person_id": 10386,
    "name": "Jim Abrahams"
  },
  {
    "movie_id": 101,
    "person_id": 10384,
    "name": "David Zucker"
  },
  {
    "movie_id": 101,
    "person_id": 10385,
    "name": "Jerry Zucker"
  },
  {
    "movie_id": 102,
    "person_id": 11690,
    "name": "Eric Appel"
  },
  {
    "movie_id": 103,
    "person_id": 11746,
    "name": "Billy Wilder"
  },
  {
    "movie_id": 104,
    "person_id": 5354,
    "name": "Joel Coen"
  },
  {
    "movie_id": 105,
    "person_id": 11534,
    "name": "Wes Anderson"
  },
  {
    "movie_id": 106,
    "person_id": 6118,
    "name": "Michael Ritchie"
  },
  {
    "movie_id": 107,
    "person_id": 2756,
    "name": "Mel Brooks"
  },
  {
    "movie_id": 108,
    "person_id": 12238,
    "name": "Ted Post"
  },
  {
    "movie_id": 109,
    "person_id": 5028,
    "name": "Brian De Palma"
  },
  {
    "movie_id": 110,
    "person_id": 12355,
    "name": "Reginald Hudlin"
  },
  {
    "movie_id": 111,
    "person_id": 12376,
    "name": "Taika Waititi"
  },
  {
    "movie_id": 112,
    "person_id": 12498,
    "name": "Tina Mackic"
  },
  {
    "movie_id": 113,
    "person_id": 12611,
    "name": "Boots Riley"
  },
  {
    "movie_id": 114,
    "person_id": 12821,
    "name": "Shaka King"
  },
  {
    "movie_id": 115,
    "person_id": 12851,
    "name": "Peter Segal"
  },
  {
    "movie_id": 116,
    "person_id": 10058,
    "name": "Steven Soderbergh"
  },
  {
    "movie_id": 117,
    "person_id": 8610,
    "name": "Clint Eastwood"
  },
  {
    "movie_id": 118,
    "person_id": 13142,
    "name": "Jared Hess"
  },
  {
    "movie_id": 119,
    "person_id": 13321,
    "name": "Phil Alden Robinson"
  },
  {
    "movie_id": 120,
    "person_id": 13443,
    "name": "Jeff Rowe"
  },
  {
    "movie_id": 121,
    "person_id": 5354,
    "name": "Joel Coen"
  },
  {
    "movie_id": 122,
    "person_id": 13632,
    "name": "Kevin Smith"
  },
  {
    "movie_id": 123,
    "person_id": 11534,
    "name": "Wes Anderson"
  },
  {
    "movie_id": 124,
    "person_id": 13790,
    "name": "Dougal Wilson"
  },
  {
    "movie_id": 125,
    "person_id": 13843,
    "name": "Edward Berger"
  },
  {
    "movie_id": 126,
    "person_id": 6892,
    "name": "Antoine Fuqua"
  },
  {
    "movie_id": 127,
    "person_id": 14214,
    "name": "Jason Reitman"
  },
  {
    "movie_id": 128,
    "person_id": 1008,
    "name": "Chris McKay"
  },
  {
    "movie_id": 129,
    "person_id": 311,
    "name": "Jorma Taccone"
  },
  {
    "movie_id": 130,
    "person_id": 13632,
    "name": "Kevin Smith"
  },
  {
    "movie_id": 131,
    "person_id": 14639,
    "name": "George Lucas"
  },
  {
    "movie_id": 132,
    "person_id": 14717,
    "name": "Trevor Peckham"
  },
  {
    "movie_id": 133,
    "person_id": 14739,
    "name": "Martin McDonagh"
  },
  {
    "movie_id": 134,
    "person_id": 14798,
    "name": "Doug Liman"
  },
  {
    "movie_id": 135,
    "person_id": 14977,
    "name": "Ted Kotcheff"
  },
  {
    "movie_id": 136,
    "person_id": 11534,
    "name": "Wes Anderson"
  },
  {
    "movie_id": 137,
    "person_id": 10444,
    "name": "Christopher Guest"
  },
  {
    "movie_id": 138,
    "person_id": 15325,
    "name": "Pete Travis"
  },
  {
    "movie_id": 139,
    "person_id": 15335,
    "name": "John Landis"
  },
  {
    "movie_id": 140,
    "person_id": 6962,
    "name": "Luc Besson"
  },
  {
    "movie_id": 141,
    "person_id": 15458,
    "name": "Jake Schreier"
  },
  {
    "movie_id": 142,
    "person_id": 15597,
    "name": "Panos Cosmatos"
  },
  {
    "movie_id": 143,
    "person_id": 5350,
    "name": "Ethan Coen"
  },
  {
    "movie_id": 143,
    "person_id": 5354,
    "name": "Joel Coen"
  },
  {
    "movie_id": 144,
    "person_id": 15755,
    "name": "Charles Crichton"
  },
  {
    "movie_id": 145,
    "person_id": 15799,
    "name": "Guillermo del Toro"
  },
  {
    "movie_id": 146,
    "person_id": 15893,
    "name": "Xavier Gens"
  },
  {
    "movie_id": 147,
    "person_id": 15569,
    "name": "Jon Watts"
  },
  {
    "movie_id": 148,
    "person_id": 11534,
    "name": "Wes Anderson"
  },
  {
    "movie_id": 149,
    "person_id": 16205,
    "name": "Michael Dowse"
  },
  {
    "movie_id": 150,
    "person_id": 16232,
    "name": "Oxide Pang Shun"
  },
  {
    "movie_id": 150,
    "person_id": 16230,
    "name": "Danny Pang"
  },
  {
    "movie_id": 151,
    "person_id": 16275,
    "name": "Irvin Kershner"
  },
  {
    "movie_id": 152,
    "person_id": 16337,
    "name": "Anthony Russo"
  },
  {
    "movie_id": 152,
    "person_id": 16340,
    "name": "Joe Russo"
  },
  {
    "movie_id": 153,
    "person_id": 16373,
    "name": "Osgood Perkins"
  },
  {
    "movie_id": 154,
    "person_id": 16511,
    "name": "Ken Finkleman"
  },
  {
    "movie_id": 155,
    "person_id": 16536,
    "name": "Steven Spielberg"
  },
  {
    "movie_id": 156,
    "person_id": 16693,
    "name": "Mark Steven Johnson"
  },
  {
    "movie_id": 157,
    "person_id": 16753,
    "name": "Brian Taylor"
  },
  {
    "movie_id": 157,
    "person_id": 16757,
    "name": "Mark Neveldine"
  },
  {
    "movie_id": 158,
    "person_id": 16536,
    "name": "Steven Spielberg"
  },
  {
    "movie_id": 159,
    "person_id": 5350,
    "name": "Ethan Coen"
  },
  {
    "movie_id": 159,
    "person_id": 5354,
    "name": "Joel Coen"
  },
  {
    "movie_id": 160,
    "person_id": 5419,
    "name": "Joe Johnston"
  },
  {
    "movie_id": 161,
    "person_id": 17159,
    "name": "Colin Trevorrow"
  },
  {
    "movie_id": 162,
    "person_id": 17502,
    "name": "J.A. Bayona"
  },
  {
    "movie_id": 163,
    "person_id": 17778,
    "name": "Kristoffer Borgli"
  },
  {
    "movie_id": 164,
    "person_id": 17887,
    "name": "Gary Ross"
  },
  {
    "movie_id": 165,
    "person_id": 17159,
    "name": "Colin Trevorrow"
  },
  {
    "movie_id": 166,
    "person_id": 18192,
    "name": "John Madden"
  },
  {
    "movie_id": 167,
    "person_id": 18218,
    "name": "Kenneth Branagh"
  },
  {
    "movie_id": 168,
    "person_id": 10124,
    "name": "Michael Bay"
  },
  {
    "movie_id": 169,
    "person_id": 10124,
    "name": "Michael Bay"
  }
]